Metadata-Version: 2.1
Name: python-cookie-shower
Version: 0.1.4
Summary: This package for Windows Users those want to know their cookies (Google Chrome)
Home-page: UNKNOWN
License: UNKNOWN
Platform: UNKNOWN
